{
  "schema_version": "a_share_v5.1",
  "report_date": "2026-07-24",
  "market_date": "2026-07-24",
  "generated_at": "2026-07-24T15:13:13+00:00",
  "provider": "daily_stock_analysis",
  "as_of": "2026-07-24",
  "data_quality": "A",
  "missing_fields": [],
  "fallback_reason": null,
  "market_summary": {
    "stock_count": 16,
    "available_quote_count": 16,
    "core_pool_count": 7,
    "watch_pool_count": 6,
    "star_pool_count": 3
  },
  "stocks": [
    {
      "code": "301217",
      "name": "铜冠铜箔",
      "close": 90.11,
      "change_pct": -3.2947,
      "amount": null,
      "turnover_rate": null,
      "ma5": 97.89,
      "ma10": 112.71,
      "ma20": 131.25,
      "volume_ratio": 0.58,
      "trend": "空头排列",
      "operation_advice": null,
      "analysis_summary": "",
      "provider": "TencentFetcher",
      "as_of": "2026-07-24",
      "data_quality": "B",
      "missing_fields": [
        "amount",
        "turnover_rate"
      ],
      "pool": "核心池"
    },
    {
      "code": "000725",
      "name": "京东方A",
      "close": 5.79,
      "change_pct": -4.4554,
      "amount": null,
      "turnover_rate": null,
      "ma5": 6.0,
      "ma10": 6.23,
      "ma20": 7.2,
      "volume_ratio": 0.6,
      "trend": "空头排列",
      "operation_advice": null,
      "analysis_summary": "",
      "provider": "TencentFetcher",
      "as_of": "2026-07-24",
      "data_quality": "B",
      "missing_fields": [
        "amount",
        "turnover_rate"
      ],
      "pool": "核心池"
    },
    {
      "code": "002384",
      "name": "东山精密",
      "close": 199.18,
      "change_pct": -3.6148,
      "amount": null,
      "turnover_rate": null,
      "ma5": 214.41,
      "ma10": 234.23,
      "ma20": 237.88,
      "volume_ratio": 0.59,
      "trend": "空头排列",
      "operation_advice": null,
      "analysis_summary": "",
      "provider": "TencentFetcher",
      "as_of": "2026-07-24",
      "data_quality": "B",
      "missing_fields": [
        "amount",
        "turnover_rate"
      ],
      "pool": "核心池"
    },
    {
      "code": "300666",
      "name": "江丰电子",
      "close": 229.47,
      "change_pct": 0.7375,
      "amount": null,
      "turnover_rate": null,
      "ma5": 225.62,
      "ma10": 249.8,
      "ma20": 300.64,
      "volume_ratio": 0.7,
      "trend": "二十日均线下方震荡",
      "operation_advice": null,
      "analysis_summary": "",
      "provider": "TencentFetcher",
      "as_of": "2026-07-24",
      "data_quality": "B",
      "missing_fields": [
        "amount",
        "turnover_rate"
      ],
      "pool": "核心池"
    },
    {
      "code": "300285",
      "name": "国瓷材料",
      "close": 60.85,
      "change_pct": 1.0294,
      "amount": null,
      "turnover_rate": null,
      "ma5": 57.5,
      "ma10": 62.68,
      "ma20": 77.78,
      "volume_ratio": 1.43,
      "trend": "二十日均线下方震荡",
      "operation_advice": null,
      "analysis_summary": "",
      "provider": "TencentFetcher",
      "as_of": "2026-07-23",
      "data_quality": "B",
      "missing_fields": [
        "amount",
        "turnover_rate"
      ],
      "pool": "核心池"
    },
    {
      "code": "000988",
      "name": "华工科技",
      "close": 111.91,
      "change_pct": -1.4096,
      "amount": null,
      "turnover_rate": null,
      "ma5": 112.41,
      "ma10": 131.01,
      "ma20": 146.31,
      "volume_ratio": 0.62,
      "trend": "空头排列",
      "operation_advice": null,
      "analysis_summary": "",
      "provider": "TencentFetcher",
      "as_of": "2026-07-23",
      "data_quality": "B",
      "missing_fields": [
        "amount",
        "turnover_rate"
      ],
      "pool": "核心池"
    },
    {
      "code": "002050",
      "name": "三花智控",
      "close": 35.05,
      "change_pct": -5.7542,
      "amount": null,
      "turnover_rate": null,
      "ma5": 36.96,
      "ma10": 39.09,
      "ma20": 41.55,
      "volume_ratio": 0.81,
      "trend": "空头排列",
      "operation_advice": null,
      "analysis_summary": "",
      "provider": "TencentFetcher",
      "as_of": "2026-07-24",
      "data_quality": "B",
      "missing_fields": [
        "amount",
        "turnover_rate"
      ],
      "pool": "核心池"
    },
    {
      "code": "603986",
      "name": "兆易创新",
      "close": 451.96,
      "change_pct": -3.8383,
      "amount": null,
      "turnover_rate": null,
      "ma5": 458.59,
      "ma10": 512.61,
      "ma20": 611.83,
      "volume_ratio": 0.69,
      "trend": "空头排列",
      "operation_advice": null,
      "analysis_summary": "",
      "provider": "TencentFetcher",
      "as_of": "2026-07-23",
      "data_quality": "B",
      "missing_fields": [
        "amount",
        "turnover_rate"
      ],
      "pool": "观察池"
    },
    {
      "code": "002371",
      "name": "北方华创",
      "close": 757.0,
      "change_pct": 2.2973,
      "amount": null,
      "turnover_rate": null,
      "ma5": 736.5,
      "ma10": 734.34,
      "ma20": 788.5,
      "volume_ratio": 0.93,
      "trend": "二十日均线下方震荡",
      "operation_advice": null,
      "analysis_summary": "",
      "provider": "TencentFetcher",
      "as_of": "2026-07-24",
      "data_quality": "B",
      "missing_fields": [
        "amount",
        "turnover_rate"
      ],
      "pool": "观察池"
    },
    {
      "code": "600584",
      "name": "长电科技",
      "close": 80.81,
      "change_pct": -5.7939,
      "amount": null,
      "turnover_rate": null,
      "ma5": 82.75,
      "ma10": 89.23,
      "ma20": 94.36,
      "volume_ratio": 0.72,
      "trend": "空头排列",
      "operation_advice": null,
      "analysis_summary": "",
      "provider": "TencentFetcher",
      "as_of": "2026-07-23",
      "data_quality": "B",
      "missing_fields": [
        "amount",
        "turnover_rate"
      ],
      "pool": "观察池"
    },
    {
      "code": "601869",
      "name": "长飞光纤",
      "close": 331.65,
      "change_pct": -6.8713,
      "amount": null,
      "turnover_rate": null,
      "ma5": 368.44,
      "ma10": 381.3,
      "ma20": 423.57,
      "volume_ratio": 0.78,
      "trend": "空头排列",
      "operation_advice": null,
      "analysis_summary": "",
      "provider": "TencentFetcher",
      "as_of": "2026-07-24",
      "data_quality": "B",
      "missing_fields": [
        "amount",
        "turnover_rate"
      ],
      "pool": "观察池"
    },
    {
      "code": "603773",
      "name": "沃格光电",
      "close": 79.88,
      "change_pct": -3.293,
      "amount": null,
      "turnover_rate": null,
      "ma5": 81.51,
      "ma10": 90.59,
      "ma20": 113.29,
      "volume_ratio": 0.67,
      "trend": "空头排列",
      "operation_advice": null,
      "analysis_summary": "",
      "provider": "TencentFetcher",
      "as_of": "2026-07-24",
      "data_quality": "B",
      "missing_fields": [
        "amount",
        "turnover_rate"
      ],
      "pool": "观察池"
    },
    {
      "code": "301095",
      "name": "广立微",
      "close": 68.5,
      "change_pct": -1.538,
      "amount": null,
      "turnover_rate": null,
      "ma5": 70.84,
      "ma10": 80.8,
      "ma20": 96.17,
      "volume_ratio": 0.5,
      "trend": "空头排列",
      "operation_advice": null,
      "analysis_summary": "",
      "provider": "TencentFetcher",
      "as_of": "2026-07-24",
      "data_quality": "B",
      "missing_fields": [
        "amount",
        "turnover_rate"
      ],
      "pool": "观察池"
    },
    {
      "code": "688361",
      "name": "中科飞测",
      "close": 357.42,
      "change_pct": 6.9032,
      "amount": null,
      "turnover_rate": null,
      "ma5": 344.12,
      "ma10": 354.54,
      "ma20": 372.42,
      "volume_ratio": 0.89,
      "trend": "二十日均线下方震荡",
      "operation_advice": null,
      "analysis_summary": "",
      "provider": "TencentFetcher",
      "as_of": "2026-07-24",
      "data_quality": "B",
      "missing_fields": [
        "amount",
        "turnover_rate"
      ],
      "pool": "科创板风向标"
    },
    {
      "code": "688072",
      "name": "拓荆科技",
      "close": 791.0,
      "change_pct": 6.4603,
      "amount": null,
      "turnover_rate": null,
      "ma5": 745.32,
      "ma10": 761.67,
      "ma20": 752.72,
      "volume_ratio": 0.87,
      "trend": "二十日均线上方震荡",
      "operation_advice": null,
      "analysis_summary": "",
      "provider": "TencentFetcher",
      "as_of": "2026-07-24",
      "data_quality": "B",
      "missing_fields": [
        "amount",
        "turnover_rate"
      ],
      "pool": "科创板风向标"
    },
    {
      "code": "688012",
      "name": "中微公司",
      "close": 388.5,
      "change_pct": 3.5448,
      "amount": null,
      "turnover_rate": null,
      "ma5": 381.42,
      "ma10": 382.44,
      "ma20": 410.16,
      "volume_ratio": 0.74,
      "trend": "二十日均线下方震荡",
      "operation_advice": null,
      "analysis_summary": "",
      "provider": "TencentFetcher",
      "as_of": "2026-07-24",
      "data_quality": "B",
      "missing_fields": [
        "amount",
        "turnover_rate"
      ],
      "pool": "科创板风向标"
    }
  ],
  "report_mode": "postmarket"
}
