{
  "schema_version": "a_share_v5.1",
  "report_date": "2026-07-20",
  "market_date": "2026-07-20",
  "generated_at": "2026-07-20T15:27:57+00:00",
  "provider": "daily_stock_analysis",
  "as_of": "2026-07-20",
  "data_quality": "A",
  "missing_fields": [],
  "fallback_reason": null,
  "market_summary": {
    "stock_count": 16,
    "available_quote_count": 16,
    "core_pool_count": 7,
    "watch_pool_count": 6,
    "star_pool_count": 3
  },
  "stocks": [
    {
      "code": "301217",
      "name": "铜冠铜箔",
      "close": 129.05,
      "change_pct": 1.4464,
      "amount": null,
      "turnover_rate": null,
      "ma5": 127.52,
      "ma10": 133.24,
      "ma20": 152.2,
      "volume_ratio": 1.48,
      "trend": "二十日均线下方震荡",
      "operation_advice": null,
      "analysis_summary": "",
      "provider": "TencentFetcher",
      "as_of": "2026-07-17",
      "data_quality": "B",
      "missing_fields": [
        "amount",
        "turnover_rate"
      ],
      "pool": "核心池"
    },
    {
      "code": "000725",
      "name": "京东方A",
      "close": 5.79,
      "change_pct": -4.6129,
      "amount": null,
      "turnover_rate": null,
      "ma5": 6.26,
      "ma10": 6.91,
      "ma20": 7.44,
      "volume_ratio": 0.91,
      "trend": "空头排列",
      "operation_advice": null,
      "analysis_summary": "",
      "provider": "TencentFetcher",
      "as_of": "2026-07-20",
      "data_quality": "B",
      "missing_fields": [
        "amount",
        "turnover_rate"
      ],
      "pool": "核心池"
    },
    {
      "code": "002384",
      "name": "东山精密",
      "close": 217.73,
      "change_pct": -9.9992,
      "amount": null,
      "turnover_rate": null,
      "ma5": 250.26,
      "ma10": 246.61,
      "ma20": 247.57,
      "volume_ratio": 0.98,
      "trend": "二十日均线下方震荡",
      "operation_advice": null,
      "analysis_summary": "",
      "provider": "TencentFetcher",
      "as_of": "2026-07-20",
      "data_quality": "B",
      "missing_fields": [
        "amount",
        "turnover_rate"
      ],
      "pool": "核心池"
    },
    {
      "code": "300666",
      "name": "江丰电子",
      "close": 199.0,
      "change_pct": -8.7323,
      "amount": null,
      "turnover_rate": null,
      "ma5": 250.11,
      "ma10": 293.67,
      "ma20": 318.26,
      "volume_ratio": 0.99,
      "trend": "空头排列",
      "operation_advice": null,
      "analysis_summary": "",
      "provider": "TencentFetcher",
      "as_of": "2026-07-20",
      "data_quality": "B",
      "missing_fields": [
        "amount",
        "turnover_rate"
      ],
      "pool": "核心池"
    },
    {
      "code": "300285",
      "name": "国瓷材料",
      "close": 56.62,
      "change_pct": -10.5529,
      "amount": null,
      "turnover_rate": null,
      "ma5": 64.37,
      "ma10": 73.09,
      "ma20": 85.23,
      "volume_ratio": 0.87,
      "trend": "空头排列",
      "operation_advice": null,
      "analysis_summary": "",
      "provider": "TencentFetcher",
      "as_of": "2026-07-17",
      "data_quality": "B",
      "missing_fields": [
        "amount",
        "turnover_rate"
      ],
      "pool": "核心池"
    },
    {
      "code": "000988",
      "name": "华工科技",
      "close": 105.86,
      "change_pct": -9.9983,
      "amount": null,
      "turnover_rate": null,
      "ma5": 131.84,
      "ma10": 143.16,
      "ma20": 154.64,
      "volume_ratio": 1.05,
      "trend": "空头排列",
      "operation_advice": null,
      "analysis_summary": "",
      "provider": "TencentFetcher",
      "as_of": "2026-07-20",
      "data_quality": "B",
      "missing_fields": [
        "amount",
        "turnover_rate"
      ],
      "pool": "核心池"
    },
    {
      "code": "002050",
      "name": "三花智控",
      "close": 36.12,
      "change_pct": -9.1321,
      "amount": null,
      "turnover_rate": null,
      "ma5": 40.17,
      "ma10": 41.46,
      "ma20": 42.69,
      "volume_ratio": 1.69,
      "trend": "空头排列",
      "operation_advice": null,
      "analysis_summary": "",
      "provider": "TencentFetcher",
      "as_of": "2026-07-20",
      "data_quality": "B",
      "missing_fields": [
        "amount",
        "turnover_rate"
      ],
      "pool": "核心池"
    },
    {
      "code": "603986",
      "name": "兆易创新",
      "close": 463.15,
      "change_pct": -9.9998,
      "amount": null,
      "turnover_rate": null,
      "ma5": 536.87,
      "ma10": 583.73,
      "ma20": 660.89,
      "volume_ratio": 1.01,
      "trend": "空头排列",
      "operation_advice": null,
      "analysis_summary": "",
      "provider": "TencentFetcher",
      "as_of": "2026-07-17",
      "data_quality": "B",
      "missing_fields": [
        "amount",
        "turnover_rate"
      ],
      "pool": "观察池"
    },
    {
      "code": "002371",
      "name": "北方华创",
      "close": 676.91,
      "change_pct": -0.0133,
      "amount": null,
      "turnover_rate": null,
      "ma5": 714.71,
      "ma10": 762.6,
      "ma20": 794.52,
      "volume_ratio": 1.16,
      "trend": "空头排列",
      "operation_advice": null,
      "analysis_summary": "",
      "provider": "TencentFetcher",
      "as_of": "2026-07-20",
      "data_quality": "B",
      "missing_fields": [
        "amount",
        "turnover_rate"
      ],
      "pool": "观察池"
    },
    {
      "code": "600584",
      "name": "长电科技",
      "close": 85.49,
      "change_pct": 2.7401,
      "amount": null,
      "turnover_rate": null,
      "ma5": 92.58,
      "ma10": 95.77,
      "ma20": 96.76,
      "volume_ratio": 1.01,
      "trend": "空头排列",
      "operation_advice": null,
      "analysis_summary": "",
      "provider": "TencentFetcher",
      "as_of": "2026-07-17",
      "data_quality": "B",
      "missing_fields": [
        "amount",
        "turnover_rate"
      ],
      "pool": "观察池"
    },
    {
      "code": "601869",
      "name": "长飞光纤",
      "close": 361.57,
      "change_pct": -9.999,
      "amount": null,
      "turnover_rate": null,
      "ma5": 394.16,
      "ma10": 410.82,
      "ma20": 470.82,
      "volume_ratio": 0.59,
      "trend": "空头排列",
      "operation_advice": null,
      "analysis_summary": "",
      "provider": "TencentFetcher",
      "as_of": "2026-07-17",
      "data_quality": "B",
      "missing_fields": [
        "amount",
        "turnover_rate"
      ],
      "pool": "观察池"
    },
    {
      "code": "603773",
      "name": "沃格光电",
      "close": 76.95,
      "change_pct": -10.0,
      "amount": null,
      "turnover_rate": null,
      "ma5": 93.46,
      "ma10": 106.21,
      "ma20": 131.24,
      "volume_ratio": 1.12,
      "trend": "空头排列",
      "operation_advice": null,
      "analysis_summary": "",
      "provider": "TencentFetcher",
      "as_of": "2026-07-20",
      "data_quality": "B",
      "missing_fields": [
        "amount",
        "turnover_rate"
      ],
      "pool": "观察池"
    },
    {
      "code": "301095",
      "name": "广立微",
      "close": 68.35,
      "change_pct": -11.886,
      "amount": null,
      "turnover_rate": null,
      "ma5": 84.41,
      "ma10": 96.25,
      "ma20": 102.34,
      "volume_ratio": 1.42,
      "trend": "空头排列",
      "operation_advice": null,
      "analysis_summary": "",
      "provider": "TencentFetcher",
      "as_of": "2026-07-20",
      "data_quality": "B",
      "missing_fields": [
        "amount",
        "turnover_rate"
      ],
      "pool": "观察池"
    },
    {
      "code": "688361",
      "name": "中科飞测",
      "close": 305.38,
      "change_pct": -1.867,
      "amount": null,
      "turnover_rate": null,
      "ma5": 348.03,
      "ma10": 376.4,
      "ma20": 365.42,
      "volume_ratio": 1.15,
      "trend": "二十日均线下方震荡",
      "operation_advice": null,
      "analysis_summary": "",
      "provider": "TencentFetcher",
      "as_of": "2026-07-20",
      "data_quality": "B",
      "missing_fields": [
        "amount",
        "turnover_rate"
      ],
      "pool": "科创板风向标"
    },
    {
      "code": "688072",
      "name": "拓荆科技",
      "close": 699.08,
      "change_pct": -3.1745,
      "amount": null,
      "turnover_rate": null,
      "ma5": 778.02,
      "ma10": 788.31,
      "ma20": 717.44,
      "volume_ratio": 0.75,
      "trend": "二十日均线下方震荡",
      "operation_advice": null,
      "analysis_summary": "",
      "provider": "TencentFetcher",
      "as_of": "2026-07-17",
      "data_quality": "B",
      "missing_fields": [
        "amount",
        "turnover_rate"
      ],
      "pool": "科创板风向标"
    },
    {
      "code": "688012",
      "name": "中微公司",
      "close": 350.69,
      "change_pct": -2.9688,
      "amount": null,
      "turnover_rate": null,
      "ma5": 383.46,
      "ma10": 408.64,
      "ma20": 411.79,
      "volume_ratio": 1.1,
      "trend": "空头排列",
      "operation_advice": null,
      "analysis_summary": "",
      "provider": "TencentFetcher",
      "as_of": "2026-07-17",
      "data_quality": "B",
      "missing_fields": [
        "amount",
        "turnover_rate"
      ],
      "pool": "科创板风向标"
    }
  ],
  "report_mode": "postmarket"
}
